doper.py
doper-1.2.0.dist-info/DESCRIPTION.rst
doper-1.2.0.dist-info/METADATA
doper-1.2.0.dist-info/RECORD
doper-1.2.0.dist-info/WHEEL
doper-1.2.0.dist-info/metadata.json
doper-1.2.0.dist-info/top_level.txt
