Metadata-Version: 2.0
Name: doper
Version: 1.2.0
Summary: A helper library for Dependency Injection
Home-page: https://github.com/alde/doper
Author: UNKNOWN
Author-email: UNKNOWN
License: Apache-2.0
Keywords: dependency injection
Platform: UNKNOWN
